cptk/__init__.py
cptk/__main__.py
cptk/commands.py
cptk/constants.py
cptk/exceptions.py
cptk/main.py
cptk/utils.py
cptk/core/__init__.py
cptk/core/chef.py
cptk/core/collector.py
cptk/core/config.py
cptk/core/fetcher.py
cptk/core/preprocessor.py
cptk/core/system.py
cptk/core/templates.py
cptk/defaults/templates/g++/.cptk/project.cptk.yaml
cptk/defaults/templates/g++/.cptk/template/{{slug(problem.name)}}.cpp
cptk/defaults/templates/py/.cptk/project.cptk.yaml
cptk/defaults/templates/py/.cptk/template/{{slug(problem.name)}}.py
cptk/local/__init__.py
cptk/local/problem.py
cptk/local/project.py
cptk/scrape/__init__.py
cptk/scrape/problem.py
cptk/scrape/website.py
cptk/websites/__init__.py
cptk/websites/codeforces.py
cptk/websites/cses.py
cptk/websites/kattis.py
cptk-0.1.0a3.dist-info/LICENSE
cptk-0.1.0a3.dist-info/METADATA
cptk-0.1.0a3.dist-info/WHEEL
cptk-0.1.0a3.dist-info/entry_points.txt
cptk-0.1.0a3.dist-info/top_level.txt
cptk-0.1.0a3.dist-info/RECORD
