Metadata-Version: 2.1
Name: cptk
Version: 0.1.0a3
Summary: Your personal assistant for everything competitive-programming-related.
Home-page: https://github.com/RealA10N/cptk
Author: Alon Krymgand Osovsky
Author-email: downtown2u@gmail.com
License: UNKNOWN
Platform: UNKNOWN
Requires-Python: >=3.7,<4
Requires-Dist: beautifulsoup4 (<5,>=4.10)
Requires-Dist: colorama (<0.5,>=0.4.3)
Requires-Dist: jinja2 (<3.1,>=3.0)
Requires-Dist: lxml (<5,>=4.6)
Requires-Dist: pydantic (<2.0,>=1.9)
Requires-Dist: python-slugify (<6,>=5.0)
Requires-Dist: pyyaml (<7.0,>=6.0)
Requires-Dist: requests (<3.0,>=2.20)
